{
  "type" : "table",
  "id" : "565f3ab7d4c6e52cfd447c77",
  "hl7Version" : "2.2",
  "libIds" : [ "573dd23bd4c6ca828c2970f5" ],
  "bindingIdentifier" : "0122",
  "name" : "0122",
  "description" : "CHARGE TYPE",
  "version" : null,
  "oid" : "UNSPECIFIED",
  "stability" : "Static",
  "extensibility" : "Closed",
  "contentDefinition" : "Extensional",
  "group" : null,
  "order" : 0,
  "codes" : [ {
    "type" : "code",
    "id" : "565f3ab7d4c6e52cfd447c78",
    "value" : "CH",
    "label" : "Charge",
    "codeSystem" : "HL70122",
    "codeSystemVersion" : null,
    "codeUsage" : "P",
    "comments" : ""
  }, {
    "type" : "code",
    "id" : "565f3ab7d4c6e52cfd447c79",
    "value" : "CO",
    "label" : "Contract",
    "codeSystem" : "HL70122",
    "codeSystemVersion" : null,
    "codeUsage" : "P",
    "comments" : ""
  }, {
    "type" : "code",
    "id" : "565f3ab7d4c6e52cfd447c7a",
    "value" : "CR",
    "label" : "Credit",
    "codeSystem" : "HL70122",
    "codeSystemVersion" : null,
    "codeUsage" : "P",
    "comments" : ""
  }, {
    "type" : "code",
    "id" : "565f3ab7d4c6e52cfd447c7b",
    "value" : "DP",
    "label" : "Department",
    "codeSystem" : "HL70122",
    "codeSystemVersion" : null,
    "codeUsage" : "P",
    "comments" : ""
  }, {
    "type" : "code",
    "id" : "565f3ab7d4c6e52cfd447c7c",
    "value" : "GR",
    "label" : "Grant",
    "codeSystem" : "HL70122",
    "codeSystemVersion" : null,
    "codeUsage" : "P",
    "comments" : ""
  }, {
    "type" : "code",
    "id" : "565f3ab7d4c6e52cfd447c7d",
    "value" : "NC",
    "label" : "No Charge",
    "codeSystem" : "HL70122",
    "codeSystemVersion" : null,
    "codeUsage" : "P",
    "comments" : ""
  }, {
    "type" : "code",
    "id" : "565f3ab7d4c6e52cfd447c7e",
    "value" : "PC",
    "label" : "Professional",
    "codeSystem" : "HL70122",
    "codeSystemVersion" : null,
    "codeUsage" : "P",
    "comments" : ""
  }, {
    "type" : "code",
    "id" : "565f3ab7d4c6e52cfd447c7f",
    "value" : "RS",
    "label" : "Research",
    "codeSystem" : "HL70122",
    "codeSystemVersion" : null,
    "codeUsage" : "P",
    "comments" : ""
  } ],
  "scope" : "HL7STANDARD",
  "accountId" : null,
  "date" : null,
  "status" : null
}