{
  "type" : "segment",
  "hl7Version" : "2.6",
  "accountId" : null,
  "scope" : "HL7STANDARD",
  "date" : null,
  "version" : null,
  "status" : null,
  "participants" : [ ],
  "libIds" : [ "573dd22fd4c6ca828c28ca5f" ],
  "predicates" : [ ],
  "conformanceStatements" : [ ],
  "id" : "569eac0ed4c623dc6550c608",
  "label" : "OBX",
  "fields" : [ {
    "type" : "field",
    "name" : "Set ID - OBX",
    "usage" : "O",
    "minLength" : 0,
    "maxLength" : "4",
    "confLength" : "",
    "table" : null,
    "datatype" : {
      "id" : "569eac0ed4c623dc6550bba3",
      "name" : "SI",
      "ext" : null,
      "label" : "SI"
    },
    "position" : 1,
    "comment" : "",
    "text" : "",
    "hide" : false,
    "id" : "569eac0ed4c623dc6550c609",
    "itemNo" : "00569",
    "min" : 0,
    "max" : "1"
  }, {
    "type" : "field",
    "name" : "Value Type",
    "usage" : "C",
    "minLength" : 0,
    "maxLength" : "3",
    "confLength" : "",
    "table" : {
      "id" : "569eac0ed4c623dc6550a5ce",
      "bindingIdentifier" : "0125",
      "bindingStrength" : null,
      "bindingLocation" : null
    },
    "datatype" : {
      "id" : "569eac0ed4c623dc6550bb77",
      "name" : "ID",
      "ext" : null,
      "label" : "ID"
    },
    "position" : 2,
    "comment" : "",
    "text" : "",
    "hide" : false,
    "id" : "569eac0ed4c623dc6550c60a",
    "itemNo" : "00570",
    "min" : 0,
    "max" : "1"
  }, {
    "type" : "field",
    "name" : "Observation Identifier",
    "usage" : "R",
    "minLength" : 0,
    "maxLength" : "705",
    "confLength" : "",
    "table" : {
      "id" : "569eac0ed4c623dc6550b131",
      "bindingIdentifier" : "9999",
      "bindingStrength" : null,
      "bindingLocation" : null
    },
    "datatype" : {
      "id" : "569eac0ed4c623dc6550bb9e",
      "name" : "CWE",
      "ext" : null,
      "label" : "CWE"
    },
    "position" : 3,
    "comment" : "",
    "text" : "",
    "hide" : false,
    "id" : "569eac0ed4c623dc6550c60b",
    "itemNo" : "00571",
    "min" : 1,
    "max" : "1"
  }, {
    "type" : "field",
    "name" : "Observation Sub-ID",
    "usage" : "C",
    "minLength" : 0,
    "maxLength" : "20",
    "confLength" : "",
    "table" : null,
    "datatype" : {
      "id" : "569eac0ed4c623dc6550bbaf",
      "name" : "ST",
      "ext" : null,
      "label" : "ST"
    },
    "position" : 4,
    "comment" : "",
    "text" : "",
    "hide" : false,
    "id" : "569eac0ed4c623dc6550c60c",
    "itemNo" : "00572",
    "min" : 0,
    "max" : "1"
  }, {
    "type" : "field",
    "name" : "Observation Value",
    "usage" : "R",
    "minLength" : 0,
    "maxLength" : "581",
    "confLength" : "",
    "table" : null,
    "datatype" : {
      "id" : "569eac0ed4c623dc6550bbad",
      "name" : "CD",
      "ext" : null,
      "label" : "CD"
    },
    "position" : 5,
    "comment" : "",
    "text" : "",
    "hide" : false,
    "id" : "569eac0ed4c623dc6550c60d",
    "itemNo" : "00573",
    "min" : 1,
    "max" : "1"
  }, {
    "type" : "field",
    "name" : "Units",
    "usage" : "X",
    "minLength" : 0,
    "maxLength" : "705",
    "confLength" : "",
    "table" : null,
    "datatype" : {
      "id" : "569eac0ed4c623dc6550bb9e",
      "name" : "CWE",
      "ext" : null,
      "label" : "CWE"
    },
    "position" : 6,
    "comment" : "",
    "text" : "",
    "hide" : false,
    "id" : "569eac0ed4c623dc6550c60e",
    "itemNo" : "00574",
    "min" : 0,
    "max" : "1"
  }, {
    "type" : "field",
    "name" : "References Range",
    "usage" : "X",
    "minLength" : 0,
    "maxLength" : "60",
    "confLength" : "",
    "table" : null,
    "datatype" : {
      "id" : "569eac0ed4c623dc6550bbaf",
      "name" : "ST",
      "ext" : null,
      "label" : "ST"
    },
    "position" : 7,
    "comment" : "",
    "text" : "",
    "hide" : false,
    "id" : "569eac0ed4c623dc6550c60f",
    "itemNo" : "00575",
    "min" : 0,
    "max" : "1"
  }, {
    "type" : "field",
    "name" : "Abnormal Flags",
    "usage" : "O",
    "minLength" : 0,
    "maxLength" : "5",
    "confLength" : "",
    "table" : {
      "id" : "569eac0ed4c623dc6550b0ff",
      "bindingIdentifier" : "0078",
      "bindingStrength" : null,
      "bindingLocation" : null
    },
    "datatype" : {
      "id" : "569eac0ed4c623dc6550bb7d",
      "name" : "IS",
      "ext" : null,
      "label" : "IS"
    },
    "position" : 8,
    "comment" : "",
    "text" : "",
    "hide" : false,
    "id" : "569eac0ed4c623dc6550c610",
    "itemNo" : "00576",
    "min" : 0,
    "max" : "*"
  }, {
    "type" : "field",
    "name" : "Probability",
    "usage" : "X",
    "minLength" : 0,
    "maxLength" : "5",
    "confLength" : "",
    "table" : null,
    "datatype" : {
      "id" : "569eac0ed4c623dc6550bb92",
      "name" : "NM",
      "ext" : null,
      "label" : "NM"
    },
    "position" : 9,
    "comment" : "",
    "text" : "",
    "hide" : false,
    "id" : "569eac0ed4c623dc6550c611",
    "itemNo" : "00577",
    "min" : 0,
    "max" : "1"
  }, {
    "type" : "field",
    "name" : "Nature of Abnormal Test",
    "usage" : "O",
    "minLength" : 0,
    "maxLength" : "2",
    "confLength" : "",
    "table" : {
      "id" : "569eac0ed4c623dc6550b0f7",
      "bindingIdentifier" : "0080",
      "bindingStrength" : null,
      "bindingLocation" : null
    },
    "datatype" : {
      "id" : "569eac0ed4c623dc6550bb77",
      "name" : "ID",
      "ext" : null,
      "label" : "ID"
    },
    "position" : 10,
    "comment" : "",
    "text" : "",
    "hide" : false,
    "id" : "569eac0ed4c623dc6550c612",
    "itemNo" : "00578",
    "min" : 0,
    "max" : "*"
  }, {
    "type" : "field",
    "name" : "Observation Result Status",
    "usage" : "R",
    "minLength" : 0,
    "maxLength" : "1",
    "confLength" : "",
    "table" : {
      "id" : "569eac0ed4c623dc6550b0e7",
      "bindingIdentifier" : "0085",
      "bindingStrength" : null,
      "bindingLocation" : null
    },
    "datatype" : {
      "id" : "569eac0ed4c623dc6550bb77",
      "name" : "ID",
      "ext" : null,
      "label" : "ID"
    },
    "position" : 11,
    "comment" : "",
    "text" : "",
    "hide" : false,
    "id" : "569eac0ed4c623dc6550c613",
    "itemNo" : "00579",
    "min" : 1,
    "max" : "1"
  }, {
    "type" : "field",
    "name" : "Effective Date of Reference Range",
    "usage" : "X",
    "minLength" : 0,
    "maxLength" : "24",
    "confLength" : "",
    "table" : null,
    "datatype" : {
      "id" : "569eac0ed4c623dc6550bb8a",
      "name" : "DTM",
      "ext" : null,
      "label" : "DTM"
    },
    "position" : 12,
    "comment" : "",
    "text" : "",
    "hide" : false,
    "id" : "569eac0ed4c623dc6550c614",
    "itemNo" : "00580",
    "min" : 0,
    "max" : "1"
  }, {
    "type" : "field",
    "name" : "User Defined Access Checks",
    "usage" : "C",
    "minLength" : 0,
    "maxLength" : "20",
    "confLength" : "",
    "table" : null,
    "datatype" : {
      "id" : "569eac0ed4c623dc6550bbaf",
      "name" : "ST",
      "ext" : null,
      "label" : "ST"
    },
    "position" : 13,
    "comment" : "",
    "text" : "",
    "hide" : false,
    "id" : "569eac0ed4c623dc6550c615",
    "itemNo" : "00581",
    "min" : 0,
    "max" : "1"
  }, {
    "type" : "field",
    "name" : "Date/Time of the Observation",
    "usage" : "X",
    "minLength" : 0,
    "maxLength" : "24",
    "confLength" : "",
    "table" : null,
    "datatype" : {
      "id" : "569eac0ed4c623dc6550bb8a",
      "name" : "DTM",
      "ext" : null,
      "label" : "DTM"
    },
    "position" : 14,
    "comment" : "",
    "text" : "",
    "hide" : false,
    "id" : "569eac0ed4c623dc6550c616",
    "itemNo" : "00582",
    "min" : 0,
    "max" : "1"
  }, {
    "type" : "field",
    "name" : "Producer's ID",
    "usage" : "X",
    "minLength" : 0,
    "maxLength" : "705",
    "confLength" : "",
    "table" : {
      "id" : "569eac0ed4c623dc6550b131",
      "bindingIdentifier" : "9999",
      "bindingStrength" : null,
      "bindingLocation" : null
    },
    "datatype" : {
      "id" : "569eac0ed4c623dc6550bb9e",
      "name" : "CWE",
      "ext" : null,
      "label" : "CWE"
    },
    "position" : 15,
    "comment" : "",
    "text" : "",
    "hide" : false,
    "id" : "569eac0ed4c623dc6550c617",
    "itemNo" : "00583",
    "min" : 0,
    "max" : "1"
  }, {
    "type" : "field",
    "name" : "Responsible Observer",
    "usage" : "O",
    "minLength" : 0,
    "maxLength" : "3220",
    "confLength" : "",
    "table" : null,
    "datatype" : {
      "id" : "569eac0ed4c623dc6550bb94",
      "name" : "XCN",
      "ext" : null,
      "label" : "XCN"
    },
    "position" : 16,
    "comment" : "",
    "text" : "",
    "hide" : false,
    "id" : "569eac0ed4c623dc6550c618",
    "itemNo" : "00584",
    "min" : 0,
    "max" : "*"
  }, {
    "type" : "field",
    "name" : "Observation Method",
    "usage" : "O",
    "minLength" : 0,
    "maxLength" : "705",
    "confLength" : "",
    "table" : null,
    "datatype" : {
      "id" : "569eac0ed4c623dc6550bb9e",
      "name" : "CWE",
      "ext" : null,
      "label" : "CWE"
    },
    "position" : 17,
    "comment" : "",
    "text" : "",
    "hide" : false,
    "id" : "569eac0ed4c623dc6550c619",
    "itemNo" : "00936",
    "min" : 0,
    "max" : "*"
  }, {
    "type" : "field",
    "name" : "Equipment Instance Identifier",
    "usage" : "O",
    "minLength" : 0,
    "maxLength" : "427",
    "confLength" : "",
    "table" : null,
    "datatype" : {
      "id" : "569eac0ed4c623dc6550bb7c",
      "name" : "EI",
      "ext" : null,
      "label" : "EI"
    },
    "position" : 18,
    "comment" : "",
    "text" : "",
    "hide" : false,
    "id" : "569eac0ed4c623dc6550c61a",
    "itemNo" : "01479",
    "min" : 0,
    "max" : "*"
  }, {
    "type" : "field",
    "name" : "Date/Time of the Analysis",
    "usage" : "O",
    "minLength" : 0,
    "maxLength" : "24",
    "confLength" : "",
    "table" : null,
    "datatype" : {
      "id" : "569eac0ed4c623dc6550bb8a",
      "name" : "DTM",
      "ext" : null,
      "label" : "DTM"
    },
    "position" : 19,
    "comment" : "",
    "text" : "",
    "hide" : false,
    "id" : "569eac0ed4c623dc6550c61b",
    "itemNo" : "01480",
    "min" : 0,
    "max" : "1"
  }, {
    "type" : "field",
    "name" : "Observation Site",
    "usage" : "O",
    "minLength" : 0,
    "maxLength" : "705",
    "confLength" : "",
    "table" : {
      "id" : "569eac0ed4c623dc6550ac7d",
      "bindingIdentifier" : "0163",
      "bindingStrength" : null,
      "bindingLocation" : null
    },
    "datatype" : {
      "id" : "569eac0ed4c623dc6550bb9e",
      "name" : "CWE",
      "ext" : null,
      "label" : "CWE"
    },
    "position" : 20,
    "comment" : "",
    "text" : "",
    "hide" : false,
    "id" : "569eac0ed4c623dc6550c61c",
    "itemNo" : "02179",
    "min" : 0,
    "max" : "*"
  }, {
    "type" : "field",
    "name" : "Observation Instance Identifier",
    "usage" : "O",
    "minLength" : 0,
    "maxLength" : "427",
    "confLength" : "",
    "table" : null,
    "datatype" : {
      "id" : "569eac0ed4c623dc6550bb7c",
      "name" : "EI",
      "ext" : null,
      "label" : "EI"
    },
    "position" : 21,
    "comment" : "",
    "text" : "",
    "hide" : false,
    "id" : "569eac0ed4c623dc6550c61d",
    "itemNo" : "02180",
    "min" : 0,
    "max" : "1"
  }, {
    "type" : "field",
    "name" : "Mood Code",
    "usage" : "C",
    "minLength" : 0,
    "maxLength" : "705",
    "confLength" : "",
    "table" : {
      "id" : "569eac0ed4c623dc6550b17b",
      "bindingIdentifier" : "0725",
      "bindingStrength" : null,
      "bindingLocation" : null
    },
    "datatype" : {
      "id" : "569eac0ed4c623dc6550bb89",
      "name" : "CNE",
      "ext" : null,
      "label" : "CNE"
    },
    "position" : 22,
    "comment" : "",
    "text" : "",
    "hide" : false,
    "id" : "569eac0ed4c623dc6550c61e",
    "itemNo" : "02182",
    "min" : 0,
    "max" : "1"
  }, {
    "type" : "field",
    "name" : "Performing Organization Name",
    "usage" : "O",
    "minLength" : 0,
    "maxLength" : "570",
    "confLength" : "",
    "table" : null,
    "datatype" : {
      "id" : "569eac0ed4c623dc6550bb84",
      "name" : "XON",
      "ext" : null,
      "label" : "XON"
    },
    "position" : 23,
    "comment" : "",
    "text" : "",
    "hide" : false,
    "id" : "569eac0ed4c623dc6550c61f",
    "itemNo" : "02283",
    "min" : 0,
    "max" : "1"
  }, {
    "type" : "field",
    "name" : "Performing Organization Address",
    "usage" : "O",
    "minLength" : 0,
    "maxLength" : "2915",
    "confLength" : "",
    "table" : null,
    "datatype" : {
      "id" : "569eac0ed4c623dc6550bbc1",
      "name" : "XAD",
      "ext" : null,
      "label" : "XAD"
    },
    "position" : 24,
    "comment" : "",
    "text" : "",
    "hide" : false,
    "id" : "569eac0ed4c623dc6550c620",
    "itemNo" : "02284",
    "min" : 0,
    "max" : "1"
  }, {
    "type" : "field",
    "name" : "Performing Organization Medical Director",
    "usage" : "O",
    "minLength" : 0,
    "maxLength" : "3220",
    "confLength" : "",
    "table" : null,
    "datatype" : {
      "id" : "569eac0ed4c623dc6550bb94",
      "name" : "XCN",
      "ext" : null,
      "label" : "XCN"
    },
    "position" : 25,
    "comment" : "",
    "text" : "",
    "hide" : false,
    "id" : "569eac0ed4c623dc6550c621",
    "itemNo" : "02285",
    "min" : 0,
    "max" : "1"
  } ],
  "dynamicMapping" : {
    "id" : "573dd22fd4c6ca828c28b5c5",
    "mappings" : [ ]
  },
  "name" : "OBX",
  "description" : "Observation/Result",
  "comment" : "",
  "text1" : "",
  "text2" : ""
}