{
  "type" : "datatype",
  "hl7Version" : "2.7",
  "accountId" : null,
  "scope" : "HL7STANDARD",
  "date" : null,
  "version" : null,
  "status" : "PUBLISHED",
  "participants" : [ ],
  "libIds" : [ "573dd232d4c6ca828c28fc9d" ],
  "predicates" : [ ],
  "conformanceStatements" : [ ],
  "id" : "569eac0dd4c623dc6550869f",
  "label" : "RMC",
  "ext" : null,
  "purposeAndUse" : null,
  "components" : [ {
    "type" : "component",
    "name" : "Room Type",
    "usage" : "R",
    "minLength" : 1,
    "maxLength" : "*",
    "confLength" : "",
    "table" : {
      "id" : "569eac0dd4c623dc65507715",
      "bindingIdentifier" : "0145",
      "bindingStrength" : null,
      "bindingLocation" : null
    },
    "datatype" : {
      "id" : "569eac0dd4c623dc65508689",
      "name" : "CWE",
      "ext" : null,
      "label" : "CWE"
    },
    "position" : 1,
    "comment" : "",
    "text" : "",
    "hide" : false,
    "id" : "569eac0dd4c623dc65508830"
  }, {
    "type" : "component",
    "name" : "Amount Type",
    "usage" : "O",
    "minLength" : 1,
    "maxLength" : "*",
    "confLength" : "",
    "table" : {
      "id" : "569eac0dd4c623dc65507722",
      "bindingIdentifier" : "0146",
      "bindingStrength" : null,
      "bindingLocation" : null
    },
    "datatype" : {
      "id" : "569eac0dd4c623dc65508689",
      "name" : "CWE",
      "ext" : null,
      "label" : "CWE"
    },
    "position" : 2,
    "comment" : "",
    "text" : "",
    "hide" : false,
    "id" : "569eac0dd4c623dc65508831"
  }, {
    "type" : "component",
    "name" : "Coverage Amount",
    "usage" : "X",
    "minLength" : 1,
    "maxLength" : "*",
    "confLength" : "",
    "table" : null,
    "datatype" : {
      "id" : "569eac0dd4c623dc6550866a",
      "name" : "-",
      "ext" : null,
      "label" : "-"
    },
    "position" : 3,
    "comment" : "",
    "text" : "",
    "hide" : false,
    "id" : "569eac0dd4c623dc65508832"
  }, {
    "type" : "component",
    "name" : "Money or Percentage",
    "usage" : "R",
    "minLength" : 1,
    "maxLength" : "*",
    "confLength" : "",
    "table" : null,
    "datatype" : {
      "id" : "569eac0dd4c623dc655086a4",
      "name" : "MOP",
      "ext" : null,
      "label" : "MOP"
    },
    "position" : 4,
    "comment" : "",
    "text" : "",
    "hide" : false,
    "id" : "569eac0dd4c623dc65508833"
  } ],
  "name" : "RMC",
  "description" : "Room Coverage",
  "comment" : "",
  "usageNote" : ""
}