{
  "type" : "datatype",
  "sectionPosition" : 110,
  "hl7Version" : "2.3",
  "accountId" : null,
  "scope" : "HL7STANDARD",
  "date" : null,
  "version" : null,
  "participants" : [ ],
  "libIds" : [ "5723765dda0805ce1eabda1c" ],
  "predicates" : [ ],
  "conformanceStatements" : [ ],
  "id" : "565f3ab7d4c6e52cfd44754a",
  "label" : "CM_OSP",
  "ext" : null,
  "components" : [ {
    "type" : "component",
    "name" : "occurrence span code",
    "usage" : "C",
    "minLength" : 0,
    "maxLength" : "-1",
    "confLength" : "",
    "table" : "",
    "bindingStrength" : "",
    "bindingLocation" : "",
    "datatype" : "565f3ab7d4c6e52cfd44756b",
    "position" : 1,
    "comment" : "",
    "text" : "",
    "hide" : false,
    "id" : "565f3ab7d4c6e52cfd447623"
  }, {
    "type" : "component",
    "name" : "occurrence span start date",
    "usage" : "C",
    "minLength" : 0,
    "maxLength" : "-1",
    "confLength" : "",
    "table" : "",
    "bindingStrength" : "",
    "bindingLocation" : "",
    "datatype" : "565f3ab7d4c6e52cfd44758f",
    "position" : 2,
    "comment" : "",
    "text" : "",
    "hide" : false,
    "id" : "565f3ab7d4c6e52cfd447624"
  }, {
    "type" : "component",
    "name" : "occurrence span stop date",
    "usage" : "C",
    "minLength" : 0,
    "maxLength" : "-1",
    "confLength" : "",
    "table" : "",
    "bindingStrength" : "",
    "bindingLocation" : "",
    "datatype" : "565f3ab7d4c6e52cfd44758f",
    "position" : 3,
    "comment" : "",
    "text" : "",
    "hide" : false,
    "id" : "565f3ab7d4c6e52cfd447625"
  } ],
  "name" : "CM_OSP",
  "description" : "occurence span",
  "comment" : "",
  "usageNote" : "",
  "status" : "PUBLISHED"
}