{
  "type" : "segment",
  "hl7Version" : "2.6",
  "accountId" : null,
  "scope" : "HL7STANDARD",
  "date" : null,
  "version" : null,
  "status" : null,
  "participants" : [ ],
  "libIds" : [ "573dd22fd4c6ca828c28ca5f" ],
  "predicates" : [ ],
  "conformanceStatements" : [ ],
  "id" : "569eac0ed4c623dc6550c25c",
  "label" : "AUT",
  "fields" : [ {
    "type" : "field",
    "name" : "Authorizing Payor, Plan ID",
    "usage" : "O",
    "minLength" : 0,
    "maxLength" : "250",
    "confLength" : "",
    "table" : {
      "id" : "569eac0ed4c623dc6550b020",
      "bindingIdentifier" : "0072",
      "bindingStrength" : null,
      "bindingLocation" : null
    },
    "datatype" : {
      "id" : "569eac0ed4c623dc6550bb9e",
      "name" : "CWE",
      "ext" : null,
      "label" : "CWE"
    },
    "position" : 1,
    "comment" : "",
    "text" : "",
    "hide" : false,
    "id" : "569eac0ed4c623dc6550c25d",
    "itemNo" : "01146",
    "min" : 0,
    "max" : "1"
  }, {
    "type" : "field",
    "name" : "Authorizing Payor, Company ID",
    "usage" : "R",
    "minLength" : 0,
    "maxLength" : "250",
    "confLength" : "",
    "table" : {
      "id" : "569eac0ed4c623dc6550acc5",
      "bindingIdentifier" : "0285",
      "bindingStrength" : null,
      "bindingLocation" : null
    },
    "datatype" : {
      "id" : "569eac0ed4c623dc6550bb9e",
      "name" : "CWE",
      "ext" : null,
      "label" : "CWE"
    },
    "position" : 2,
    "comment" : "",
    "text" : "",
    "hide" : false,
    "id" : "569eac0ed4c623dc6550c25e",
    "itemNo" : "01147",
    "min" : 1,
    "max" : "1"
  }, {
    "type" : "field",
    "name" : "Authorizing Payor, Company Name",
    "usage" : "O",
    "minLength" : 0,
    "maxLength" : "45",
    "confLength" : "",
    "table" : null,
    "datatype" : {
      "id" : "569eac0ed4c623dc6550bbaf",
      "name" : "ST",
      "ext" : null,
      "label" : "ST"
    },
    "position" : 3,
    "comment" : "",
    "text" : "",
    "hide" : false,
    "id" : "569eac0ed4c623dc6550c25f",
    "itemNo" : "01148",
    "min" : 0,
    "max" : "1"
  }, {
    "type" : "field",
    "name" : "Authorization Effective Date",
    "usage" : "O",
    "minLength" : 0,
    "maxLength" : "24",
    "confLength" : "",
    "table" : null,
    "datatype" : {
      "id" : "569eac0ed4c623dc6550bb8a",
      "name" : "DTM",
      "ext" : null,
      "label" : "DTM"
    },
    "position" : 4,
    "comment" : "",
    "text" : "",
    "hide" : false,
    "id" : "569eac0ed4c623dc6550c260",
    "itemNo" : "01149",
    "min" : 0,
    "max" : "1"
  }, {
    "type" : "field",
    "name" : "Authorization Expiration Date",
    "usage" : "O",
    "minLength" : 0,
    "maxLength" : "24",
    "confLength" : "",
    "table" : null,
    "datatype" : {
      "id" : "569eac0ed4c623dc6550bb8a",
      "name" : "DTM",
      "ext" : null,
      "label" : "DTM"
    },
    "position" : 5,
    "comment" : "",
    "text" : "",
    "hide" : false,
    "id" : "569eac0ed4c623dc6550c261",
    "itemNo" : "01150",
    "min" : 0,
    "max" : "1"
  }, {
    "type" : "field",
    "name" : "Authorization Identifier",
    "usage" : "C",
    "minLength" : 0,
    "maxLength" : "30",
    "confLength" : "",
    "table" : null,
    "datatype" : {
      "id" : "569eac0ed4c623dc6550bb7c",
      "name" : "EI",
      "ext" : null,
      "label" : "EI"
    },
    "position" : 6,
    "comment" : "",
    "text" : "",
    "hide" : false,
    "id" : "569eac0ed4c623dc6550c262",
    "itemNo" : "01151",
    "min" : 0,
    "max" : "1"
  }, {
    "type" : "field",
    "name" : "Reimbursement Limit",
    "usage" : "O",
    "minLength" : 0,
    "maxLength" : "25",
    "confLength" : "",
    "table" : null,
    "datatype" : {
      "id" : "569eac0ed4c623dc6550bbb7",
      "name" : "CP",
      "ext" : null,
      "label" : "CP"
    },
    "position" : 7,
    "comment" : "",
    "text" : "",
    "hide" : false,
    "id" : "569eac0ed4c623dc6550c263",
    "itemNo" : "01152",
    "min" : 0,
    "max" : "1"
  }, {
    "type" : "field",
    "name" : "Requested Number of Treatments",
    "usage" : "O",
    "minLength" : 0,
    "maxLength" : "2",
    "confLength" : "",
    "table" : null,
    "datatype" : {
      "id" : "569eac0ed4c623dc6550bb92",
      "name" : "NM",
      "ext" : null,
      "label" : "NM"
    },
    "position" : 8,
    "comment" : "",
    "text" : "",
    "hide" : false,
    "id" : "569eac0ed4c623dc6550c264",
    "itemNo" : "01153",
    "min" : 0,
    "max" : "1"
  }, {
    "type" : "field",
    "name" : "Authorized Number of Treatments",
    "usage" : "O",
    "minLength" : 0,
    "maxLength" : "2",
    "confLength" : "",
    "table" : null,
    "datatype" : {
      "id" : "569eac0ed4c623dc6550bb92",
      "name" : "NM",
      "ext" : null,
      "label" : "NM"
    },
    "position" : 9,
    "comment" : "",
    "text" : "",
    "hide" : false,
    "id" : "569eac0ed4c623dc6550c265",
    "itemNo" : "01154",
    "min" : 0,
    "max" : "1"
  }, {
    "type" : "field",
    "name" : "Process Date",
    "usage" : "O",
    "minLength" : 0,
    "maxLength" : "24",
    "confLength" : "",
    "table" : null,
    "datatype" : {
      "id" : "569eac0ed4c623dc6550bb8a",
      "name" : "DTM",
      "ext" : null,
      "label" : "DTM"
    },
    "position" : 10,
    "comment" : "",
    "text" : "",
    "hide" : false,
    "id" : "569eac0ed4c623dc6550c266",
    "itemNo" : "01145",
    "min" : 0,
    "max" : "1"
  } ],
  "dynamicMapping" : {
    "id" : "573dd22fd4c6ca828c28b500",
    "mappings" : [ ]
  },
  "name" : "AUT",
  "description" : "Authorization Information",
  "comment" : "",
  "text1" : "",
  "text2" : ""
}