{
  "type" : "table",
  "id" : "565f3ab6d4c6e52cfd44167b",
  "hl7Version" : "2.5",
  "libIds" : [ "573dd235d4c6ca828c292649" ],
  "bindingIdentifier" : "0119",
  "name" : "0119",
  "description" : "Order control codes",
  "version" : null,
  "oid" : "2.16.840.1.113883.12.119",
  "stability" : "Static",
  "extensibility" : "Closed",
  "contentDefinition" : "Extensional",
  "group" : null,
  "order" : 0,
  "codes" : [ {
    "type" : "code",
    "id" : "565f3ab6d4c6e52cfd44167c",
    "value" : "AF",
    "label" : "Order/service refill request approval",
    "codeSystem" : "HL70119",
    "codeSystemVersion" : null,
    "codeUsage" : "P",
    "comments" : ""
  }, {
    "type" : "code",
    "id" : "565f3ab6d4c6e52cfd44167d",
    "value" : "CA",
    "label" : "Cancel order/service request",
    "codeSystem" : "HL70119",
    "codeSystemVersion" : null,
    "codeUsage" : "P",
    "comments" : ""
  }, {
    "type" : "code",
    "id" : "565f3ab6d4c6e52cfd44167e",
    "value" : "CH",
    "label" : "Child order/service",
    "codeSystem" : "HL70119",
    "codeSystemVersion" : null,
    "codeUsage" : "P",
    "comments" : ""
  }, {
    "type" : "code",
    "id" : "565f3ab6d4c6e52cfd44167f",
    "value" : "CN",
    "label" : "Combined result",
    "codeSystem" : "HL70119",
    "codeSystemVersion" : null,
    "codeUsage" : "P",
    "comments" : ""
  }, {
    "type" : "code",
    "id" : "565f3ab6d4c6e52cfd441680",
    "value" : "CR",
    "label" : "Canceled as requested",
    "codeSystem" : "HL70119",
    "codeSystemVersion" : null,
    "codeUsage" : "P",
    "comments" : ""
  }, {
    "type" : "code",
    "id" : "565f3ab6d4c6e52cfd441681",
    "value" : "DC",
    "label" : "Discontinue order/service request",
    "codeSystem" : "HL70119",
    "codeSystemVersion" : null,
    "codeUsage" : "P",
    "comments" : ""
  }, {
    "type" : "code",
    "id" : "565f3ab6d4c6e52cfd441682",
    "value" : "DE",
    "label" : "Data errors",
    "codeSystem" : "HL70119",
    "codeSystemVersion" : null,
    "codeUsage" : "P",
    "comments" : ""
  }, {
    "type" : "code",
    "id" : "565f3ab6d4c6e52cfd441683",
    "value" : "DF",
    "label" : "Order/service refill request denied",
    "codeSystem" : "HL70119",
    "codeSystemVersion" : null,
    "codeUsage" : "P",
    "comments" : ""
  }, {
    "type" : "code",
    "id" : "565f3ab6d4c6e52cfd441684",
    "value" : "DR",
    "label" : "Discontinued as requested",
    "codeSystem" : "HL70119",
    "codeSystemVersion" : null,
    "codeUsage" : "P",
    "comments" : ""
  }, {
    "type" : "code",
    "id" : "565f3ab6d4c6e52cfd441685",
    "value" : "FU",
    "label" : "Order/service refilled, unsolicited",
    "codeSystem" : "HL70119",
    "codeSystemVersion" : null,
    "codeUsage" : "P",
    "comments" : ""
  }, {
    "type" : "code",
    "id" : "565f3ab6d4c6e52cfd441686",
    "value" : "HD",
    "label" : "Hold order request",
    "codeSystem" : "HL70119",
    "codeSystemVersion" : null,
    "codeUsage" : "P",
    "comments" : ""
  }, {
    "type" : "code",
    "id" : "565f3ab6d4c6e52cfd441687",
    "value" : "HR",
    "label" : "On hold as requested",
    "codeSystem" : "HL70119",
    "codeSystemVersion" : null,
    "codeUsage" : "P",
    "comments" : ""
  }, {
    "type" : "code",
    "id" : "565f3ab6d4c6e52cfd441688",
    "value" : "LI",
    "label" : "Link order/service to patient care problem or goal",
    "codeSystem" : "HL70119",
    "codeSystemVersion" : null,
    "codeUsage" : "P",
    "comments" : ""
  }, {
    "type" : "code",
    "id" : "565f3ab6d4c6e52cfd441689",
    "value" : "NA",
    "label" : "Number assigned",
    "codeSystem" : "HL70119",
    "codeSystemVersion" : null,
    "codeUsage" : "P",
    "comments" : ""
  }, {
    "type" : "code",
    "id" : "565f3ab6d4c6e52cfd44168a",
    "value" : "NW",
    "label" : "New order/service",
    "codeSystem" : "HL70119",
    "codeSystemVersion" : null,
    "codeUsage" : "P",
    "comments" : ""
  }, {
    "type" : "code",
    "id" : "565f3ab6d4c6e52cfd44168b",
    "value" : "OC",
    "label" : "Order/service canceled",
    "codeSystem" : "HL70119",
    "codeSystemVersion" : null,
    "codeUsage" : "P",
    "comments" : ""
  }, {
    "type" : "code",
    "id" : "565f3ab6d4c6e52cfd44168c",
    "value" : "OD",
    "label" : "Order/service discontinued",
    "codeSystem" : "HL70119",
    "codeSystemVersion" : null,
    "codeUsage" : "P",
    "comments" : ""
  }, {
    "type" : "code",
    "id" : "565f3ab6d4c6e52cfd44168d",
    "value" : "OE",
    "label" : "Order/service released",
    "codeSystem" : "HL70119",
    "codeSystemVersion" : null,
    "codeUsage" : "P",
    "comments" : ""
  }, {
    "type" : "code",
    "id" : "565f3ab6d4c6e52cfd44168e",
    "value" : "OF",
    "label" : "Order/service refilled as requested",
    "codeSystem" : "HL70119",
    "codeSystemVersion" : null,
    "codeUsage" : "P",
    "comments" : ""
  }, {
    "type" : "code",
    "id" : "565f3ab6d4c6e52cfd44168f",
    "value" : "OH",
    "label" : "Order/service held",
    "codeSystem" : "HL70119",
    "codeSystemVersion" : null,
    "codeUsage" : "P",
    "comments" : ""
  }, {
    "type" : "code",
    "id" : "565f3ab6d4c6e52cfd441690",
    "value" : "OK",
    "label" : "Order/service accepted & OK",
    "codeSystem" : "HL70119",
    "codeSystemVersion" : null,
    "codeUsage" : "P",
    "comments" : ""
  }, {
    "type" : "code",
    "id" : "565f3ab6d4c6e52cfd441691",
    "value" : "OP",
    "label" : "Notification of order for outside dispense",
    "codeSystem" : "HL70119",
    "codeSystemVersion" : null,
    "codeUsage" : "P",
    "comments" : ""
  }, {
    "type" : "code",
    "id" : "565f3ab6d4c6e52cfd441692",
    "value" : "OR",
    "label" : "Released as requested",
    "codeSystem" : "HL70119",
    "codeSystemVersion" : null,
    "codeUsage" : "P",
    "comments" : ""
  }, {
    "type" : "code",
    "id" : "565f3ab6d4c6e52cfd441693",
    "value" : "PA",
    "label" : "Parent order/service",
    "codeSystem" : "HL70119",
    "codeSystemVersion" : null,
    "codeUsage" : "P",
    "comments" : ""
  }, {
    "type" : "code",
    "id" : "565f3ab6d4c6e52cfd441694",
    "value" : "PR",
    "label" : "Previous Results with new order/service",
    "codeSystem" : "HL70119",
    "codeSystemVersion" : null,
    "codeUsage" : "P",
    "comments" : ""
  }, {
    "type" : "code",
    "id" : "565f3ab6d4c6e52cfd441695",
    "value" : "PY",
    "label" : "Notification of replacement order for outside dispense",
    "codeSystem" : "HL70119",
    "codeSystemVersion" : null,
    "codeUsage" : "P",
    "comments" : ""
  }, {
    "type" : "code",
    "id" : "565f3ab6d4c6e52cfd441696",
    "value" : "RE",
    "label" : "Observations/Performed Service to follow",
    "codeSystem" : "HL70119",
    "codeSystemVersion" : null,
    "codeUsage" : "P",
    "comments" : ""
  }, {
    "type" : "code",
    "id" : "565f3ab6d4c6e52cfd441697",
    "value" : "RF",
    "label" : "Refill order/service request",
    "codeSystem" : "HL70119",
    "codeSystemVersion" : null,
    "codeUsage" : "P",
    "comments" : ""
  }, {
    "type" : "code",
    "id" : "565f3ab6d4c6e52cfd441698",
    "value" : "RL",
    "label" : "Release previous hold",
    "codeSystem" : "HL70119",
    "codeSystemVersion" : null,
    "codeUsage" : "P",
    "comments" : ""
  }, {
    "type" : "code",
    "id" : "565f3ab6d4c6e52cfd441699",
    "value" : "RO",
    "label" : "Replacement order",
    "codeSystem" : "HL70119",
    "codeSystemVersion" : null,
    "codeUsage" : "P",
    "comments" : ""
  }, {
    "type" : "code",
    "id" : "565f3ab6d4c6e52cfd44169a",
    "value" : "RP",
    "label" : "Order/service replace request",
    "codeSystem" : "HL70119",
    "codeSystemVersion" : null,
    "codeUsage" : "P",
    "comments" : ""
  }, {
    "type" : "code",
    "id" : "565f3ab6d4c6e52cfd44169b",
    "value" : "RQ",
    "label" : "Replaced as requested",
    "codeSystem" : "HL70119",
    "codeSystemVersion" : null,
    "codeUsage" : "P",
    "comments" : ""
  }, {
    "type" : "code",
    "id" : "565f3ab6d4c6e52cfd44169c",
    "value" : "RR",
    "label" : "Request received",
    "codeSystem" : "HL70119",
    "codeSystemVersion" : null,
    "codeUsage" : "P",
    "comments" : ""
  }, {
    "type" : "code",
    "id" : "565f3ab6d4c6e52cfd44169d",
    "value" : "RU",
    "label" : "Replaced unsolicited",
    "codeSystem" : "HL70119",
    "codeSystemVersion" : null,
    "codeUsage" : "P",
    "comments" : ""
  }, {
    "type" : "code",
    "id" : "565f3ab6d4c6e52cfd44169e",
    "value" : "SC",
    "label" : "Status changed",
    "codeSystem" : "HL70119",
    "codeSystemVersion" : null,
    "codeUsage" : "P",
    "comments" : ""
  }, {
    "type" : "code",
    "id" : "565f3ab6d4c6e52cfd44169f",
    "value" : "SN",
    "label" : "Send order/service number",
    "codeSystem" : "HL70119",
    "codeSystemVersion" : null,
    "codeUsage" : "P",
    "comments" : ""
  }, {
    "type" : "code",
    "id" : "565f3ab6d4c6e52cfd4416a0",
    "value" : "SR",
    "label" : "Response to send order/service status request",
    "codeSystem" : "HL70119",
    "codeSystemVersion" : null,
    "codeUsage" : "P",
    "comments" : ""
  }, {
    "type" : "code",
    "id" : "565f3ab6d4c6e52cfd4416a1",
    "value" : "SS",
    "label" : "Send order/service status request",
    "codeSystem" : "HL70119",
    "codeSystemVersion" : null,
    "codeUsage" : "P",
    "comments" : ""
  }, {
    "type" : "code",
    "id" : "565f3ab6d4c6e52cfd4416a2",
    "value" : "UA",
    "label" : "Unable to accept order/service",
    "codeSystem" : "HL70119",
    "codeSystemVersion" : null,
    "codeUsage" : "P",
    "comments" : ""
  }, {
    "type" : "code",
    "id" : "565f3ab6d4c6e52cfd4416a3",
    "value" : "UC",
    "label" : "Unable to cancel",
    "codeSystem" : "HL70119",
    "codeSystemVersion" : null,
    "codeUsage" : "P",
    "comments" : ""
  }, {
    "type" : "code",
    "id" : "565f3ab6d4c6e52cfd4416a4",
    "value" : "UD",
    "label" : "Unable to discontinue",
    "codeSystem" : "HL70119",
    "codeSystemVersion" : null,
    "codeUsage" : "P",
    "comments" : ""
  }, {
    "type" : "code",
    "id" : "565f3ab6d4c6e52cfd4416a5",
    "value" : "UF",
    "label" : "Unable to refill",
    "codeSystem" : "HL70119",
    "codeSystemVersion" : null,
    "codeUsage" : "P",
    "comments" : ""
  }, {
    "type" : "code",
    "id" : "565f3ab6d4c6e52cfd4416a6",
    "value" : "UH",
    "label" : "Unable to put on hold",
    "codeSystem" : "HL70119",
    "codeSystemVersion" : null,
    "codeUsage" : "P",
    "comments" : ""
  }, {
    "type" : "code",
    "id" : "565f3ab6d4c6e52cfd4416a7",
    "value" : "UM",
    "label" : "Unable to replace",
    "codeSystem" : "HL70119",
    "codeSystemVersion" : null,
    "codeUsage" : "P",
    "comments" : ""
  }, {
    "type" : "code",
    "id" : "565f3ab6d4c6e52cfd4416a8",
    "value" : "UN",
    "label" : "Unlink order/service from patient care problem or goal",
    "codeSystem" : "HL70119",
    "codeSystemVersion" : null,
    "codeUsage" : "P",
    "comments" : ""
  }, {
    "type" : "code",
    "id" : "565f3ab6d4c6e52cfd4416a9",
    "value" : "UR",
    "label" : "Unable to release",
    "codeSystem" : "HL70119",
    "codeSystemVersion" : null,
    "codeUsage" : "P",
    "comments" : ""
  }, {
    "type" : "code",
    "id" : "565f3ab6d4c6e52cfd4416aa",
    "value" : "UX",
    "label" : "Unable to change",
    "codeSystem" : "HL70119",
    "codeSystemVersion" : null,
    "codeUsage" : "P",
    "comments" : ""
  }, {
    "type" : "code",
    "id" : "565f3ab6d4c6e52cfd4416ab",
    "value" : "XO",
    "label" : "Change order/service request",
    "codeSystem" : "HL70119",
    "codeSystemVersion" : null,
    "codeUsage" : "P",
    "comments" : ""
  }, {
    "type" : "code",
    "id" : "565f3ab6d4c6e52cfd4416ac",
    "value" : "XR",
    "label" : "Changed as requested",
    "codeSystem" : "HL70119",
    "codeSystemVersion" : null,
    "codeUsage" : "P",
    "comments" : ""
  }, {
    "type" : "code",
    "id" : "565f3ab6d4c6e52cfd4416ad",
    "value" : "XX",
    "label" : "Order/service changed, unsol.",
    "codeSystem" : "HL70119",
    "codeSystemVersion" : null,
    "codeUsage" : "P",
    "comments" : ""
  } ],
  "scope" : "HL7STANDARD",
  "accountId" : null,
  "date" : null,
  "status" : null
}